exinc/__init__.py
exinc/default_config.py
exinc/optimizer.py
exinc/preprocessor.py
exinc/tool.py
exinc-1.0.3.dist-info/METADATA
exinc-1.0.3.dist-info/WHEEL
exinc-1.0.3.dist-info/entry_points.txt
exinc-1.0.3.dist-info/RECORD
