Metadata-Version: 2.1
Name: exinc
Version: 1.0.3
Summary: Tool to expand C++ includes targeting competitive programmers.
Author: Roberto Sales
Author-email: rsalescaldeira@gmail.com
Requires-Python: >=3.10,<4.0
Classifier: Programming Language :: Python :: 3
Classifier: Programming Language :: Python :: 3.10
Classifier: Programming Language :: Python :: 3.11
Classifier: Programming Language :: Python :: 3.12
